playpy/LICENSE
playpy/README.md
playpy/__init__.py
playpy/playpy.py
playpy/plp_utils.py
playpy-1.0.1.dist-info/METADATA
playpy-1.0.1.dist-info/WHEEL
playpy-1.0.1.dist-info/RECORD
